[
    {
      "total": 3982,
      "sector": "Región Aisén del Gral.Carlos Ibáñez del Campo"
    },
    {
      "total": 16908,
      "sector": "Región de Antofagasta"
    },
    {
      "total": 8697,
      "sector": "Región de Arica y Parinacota"
    },
    {
      "total": 7392,
      "sector": "Región de Atacama"
    },
    {
      "total": 17030,
      "sector": "Región de Coquimbo"
    },
    {
      "total": 27828,
      "sector": "Región de La Araucanía"
    },
    {
      "total": 30661,
      "sector": "Región de Los Lagos"
    },
    {
      "total": 10941,
      "sector": "Región de Los Ríos"
    },
    {
      "total": 7232,
      "sector": "Región de Magallanes y de la Antártica Chilena"
    },
    {
      "total": 13787,
      "sector": "Región de Ñuble"
    },
    {
      "total": 10400,
      "sector": "Región de Tarapacá"
    },
    {
      "total": 53781,
      "sector": "Región de Valparaíso"
    },
    {
      "total": 44081,
      "sector": "Región del Biobío"
    },
    {
      "total": 27275,
      "sector": "Región del Libertador Gral. Bernardo O’Higgins"
    },
    {
      "total": 37205,
      "sector": "Región del Maule"
    },
    {
      "total": 196702,
      "sector": "Región Metropolitana de Santiago"
    }
  ]